edclasses/__init__.py
edclasses/api_clients.py
edclasses/classes.py
edclasses/enums.py
edclasses/models.py
edclasses/utils.py
edclasses/api_adapters/__init__.py
edclasses/api_adapters/elite_bgs_adapter.py
edclasses/api_adapters/utils.py
edclasses/commons/__init__.py
edclasses/commons/caching_utils.py
edclasses/tests/__init__.py
edclasses/tests/mocked_adapter.py
edclasses/tests/test_classes.py
edclasses/tests/test_relations.py
edclasses/tests/factories/__init__.py
edclasses/tests/factories/classes_factories.py
elite_dangerous_classes_library-0.1.0.dist-info/LICENSE.md
elite_dangerous_classes_library-0.1.0.dist-info/METADATA
elite_dangerous_classes_library-0.1.0.dist-info/WHEEL
elite_dangerous_classes_library-0.1.0.dist-info/top_level.txt
elite_dangerous_classes_library-0.1.0.dist-info/RECORD
