Metadata-Version: 2.1
Name: elite-dangerous-classes-library
Version: 0.1.0
Summary: Library representing various objects in Elite Dangerous
Author-email: Michał Karaś <mjkaras93@gmail.com>
License: MIT License        
Project-URL: Homepage, https://github.com/MKaras93/elite-dangerous-classes-library
Keywords: elite dangerous
Classifier: License :: OSI Approved :: MIT License
Classifier: Programming Language :: Python
Classifier: Programming Language :: Python :: 3
Requires-Python: >=3.9
License-File: LICENSE.md
Requires-Dist: ratelimit (>=2.2.1)
Requires-Dist: requests (>=2.27.1)
Provides-Extra: dev
Requires-Dist: pytest (>=6.2.5) ; extra == 'dev'
Requires-Dist: pytest-factoryboy (>=2.1.0) ; extra == 'dev'
